word_to_pronunciation/__init__.py
word_to_pronunciation/api.py
word_to_pronunciation/core.py
word_to_pronunciation/types.py
word_to_pronunciation/utils.py
word_to_pronunciation-0.0.1.dist-info/LICENSE
word_to_pronunciation-0.0.1.dist-info/METADATA
word_to_pronunciation-0.0.1.dist-info/WHEEL
word_to_pronunciation-0.0.1.dist-info/entry_points.txt
word_to_pronunciation-0.0.1.dist-info/top_level.txt
word_to_pronunciation-0.0.1.dist-info/RECORD
