Metadata-Version: 2.1
Name: word-to-pronunciation
Version: 0.0.1
Summary: Create pronunciations of words with the possibility of ignoring punctuation and splitting on hyphens before lookup.
Home-page: https://github.com/stefantaubert/sentence2pronunciation
Author: Stefan Taubert
Author-email: stefan.taubert@posteo.me
Maintainer: Stefan Taubert
Maintainer-email: stefan.taubert@posteo.me
License: MIT
Project-URL: Homepage, https://github.com/stefantaubert/sentence2pronunciation
Project-URL: Issues, https://github.com/stefantaubert/sentence2pronunciation/issues
Keywords: Language,Linguistics
Platform: UNKNOWN
Classifier: Development Status :: 2 - Pre-Alpha
Classifier: Operating System :: OS Independent
Classifier: Operating System :: MacOS
Classifier: Operating System :: POSIX
Classifier: Operating System :: POSIX :: BSD
Classifier: Operating System :: POSIX :: Linux
Classifier: Operating System :: Unix
Classifier: Operating System :: Microsoft :: Windows
Classifier: Programming Language :: Python
Classifier: Programming Language :: Python :: 3
Classifier: Programming Language :: Python :: 3.6
Classifier: Programming Language :: Python :: 3.7
Classifier: Programming Language :: Python :: 3.8
Classifier: Programming Language :: Python :: 3.9
Classifier: Programming Language :: Python :: 3.10
Classifier: License :: OSI Approved :: MIT License
Requires-Python: >=3.6
License-File: LICENSE
Requires-Dist: pronunciation-dictionary (>=0.0.3)
